eromedownloader/__init__.py
eromedownloader/__main__.py
eromedownloader/save_dir.py
eromedownloader-0.0.1.dist-info/WHEEL
eromedownloader-0.0.1.dist-info/METADATA
eromedownloader-0.0.1.dist-info/LICENSE
eromedownloader-0.0.1.dist-info/RECORD
