Metadata-Version: 2.1
Name: eromedownloader
Version: 0.0.1
Summary: A Downloader for erome.com
Home-page: https://github.com/masteroftheskies/eromedownloader
License: MIT
Keywords: erome,scraping,downloader
Author: masteroftheskies
Author-email: masteroftheskies@proton.me
Requires-Python: >=3.11,<4.0
Classifier: License :: OSI Approved :: MIT License
Classifier: Operating System :: OS Independent
Classifier: Programming Language :: Python :: 3
Classifier: Programming Language :: Python :: 3.11
Classifier: Programming Language :: Python :: 3
Requires-Dist: aiofiles
Requires-Dist: aiohttp
Requires-Dist: beautifulsoup4
Requires-Dist: requests
Requires-Dist: tqdm
Project-URL: Repository, https://github.com/masteroftheskies/eromedownloader
